[
    {
        "id": 1,
        "PN":"UPS204DH33A2V35",
        "name": "DPH G2 200",
        "price": 15706.96,
        "maxLoad": 200,
        "defaultLoad": 200,
        "NumofBlocksinOneString": [30, 32, 34, 36, 38, 40, 42, 44, 46],
        "dcEfficiency": [83.5, 93.09, 94.74, 95.35, 95.48, 95.53, 95.49, 95.40, 95.27, 95.17, 95.09],
        "image": "/assets/ups/DPH_G2_200.jpg",
        "description": "DPH Gen.2 200kVA FR (42U), 3 phase in, 3 phase out, 230V/50 Hz, without battery, parallel function.",
        "modular": true,
        "PM": "3915101540-S"
    },
    {
        "id": 5,
        "PN":"UPS304DH33A2035",
        "name": "DPH 300",
        "price": 17432.82,
        "maxLoad": 300,
        "defaultLoad": 300,
        "NumofBlocksinOneString": [30, 32, 34, 36, 38, 40, 42, 44, 46],
        "dcEfficiency": [83.5, 93.09, 94.75, 95.35, 95.48, 95.53, 95.49, 95.40, 95.27, 95.17, 95.09],
        "image": "/assets/ups/DPH300-600.jpg",
        "description": "DPH 300kVA / 300kW System Chassis, 3 phase in, 3 phase out, 230V/50 Hz, without battery, parallel function.",
        "modular": true,
        "PM": "3915101540-S"
    },
    {
        "id": 6,
        "PN":"UPS504DH33A1035",
        "name": "DPH 500",
        "price": 21122.31,
        "maxLoad": 450,
        "defaultLoad": 360,
        "NumofBlocksinOneString": [30, 32, 34, 36, 38, 40, 42, 44, 46],
        "dcEfficiency": [83.5, 93.09, 94.75, 95.35, 95.48, 95.53, 95.49, 95.4, 95.27, 95.17, 95.09],
        "image": "/assets/ups/DPH500.jpg",
        "description": "DPH 500kVA / 450kW, 3 phase in, 3 phase out, 230V/50 Hz, without battery, parallel function.",
        "modular": true,
        "PM": "3915101540-S"
    },
    {
        "id": 7,
        "PN":"UPS604DH33A2035",
        "name": "DPH 600",
        "price": 31527,
        "maxLoad": 600,
        "defaultLoad": 600,
        "NumofBlocksinOneString": [30, 32, 34, 36, 38, 40, 42, 44, 46],
        "dcEfficiency": [83.5, 93.09, 94.75, 95.35, 95.48, 95.53, 95.49, 95.40, 95.27, 95.17, 95.09],
        "image": "/assets/ups/DPH300-600.jpg",
        "description": "DPH 600kVA / 600kW System Chassis, 3 phase in, 3 phase out, 230V/50 Hz, without battery, parallel function.",
        "modular": true,
        "PM": "3915101540-S"
    },
    {
        "id": 9,
        "PN":"UPS803DH33C2035",
        "name": "DPH 80",
        "price": 6961.74,
        "maxLoad": 80,
        "defaultLoad": 64,
        "NumofBlocksinOneString": [32, 34, 36, 38, 40, 42, 44, 46],
        "dcEfficiency": [83.5, 87, 89.4, 90.8, 92.15, 93.50, 93.84, 94.18, 94.49, 94.76, 95.04],
        "image": "/assets/ups/DPH80-200.jpg",
        "description": "DPH 80kVA / 80 kW System Chassis, 3 phase in, 3 phase out, 230V/50 Hz, without battery, parallel function.",
        "modular": true,
        "PM": "3915102002-S"
    },
    {
        "id": 2,
        "PN":"UPS124DH33C2035",
        "name": "DPH 120",
        "price": 8501.77,
        "maxLoad": 120,
        "defaultLoad": 96,
        "NumofBlocksinOneString": [32, 34, 36, 38, 40, 42, 44, 46],
        "dcEfficiency": [83.5, 90.12, 93, 93.84, 94.03, 94.23, 94.34, 94.45, 94.57, 94.71, 94.85],
        "image": "/assets/ups/DPH80-120.jpg",
        "description": "DPH 120kVA / 120 kW System Chassis, 3 phase in, 3 phase out, 230V/50 Hz, without battery, parallel function.",
        "modular": true,
        "PM": "3915102002-S"
    },
    {
        "id": 10,
        "PN":"UPS304DS3312A35",
        "name": "DPS 300",
        "price": 33956.04,
        "maxLoad": 300,
        "defaultLoad": 240,
        "NumofBlocksinOneString": [30, 32, 34, 36, 38, 40, 42, 44, 46],
        "dcEfficiency": [83.5, 93.09, 94.75, 95.35, 95.48, 95.53, 95.49, 95.4, 95.27, 95.17, 95.09],
        "image": "/assets/ups/DPS300-1200.jpg",
        "description": "DPS Series, 3 phase in, 3 phase out, 230V 50 Hz, without battery, parallel function.",
        "modular": false,
        "PM": "N/A"
    },
    {
        "id": 11,
        "PN":"UPS404DS3312A35",
        "name": "DPS 400",
        "price": 46783.88,
        "maxLoad": 400,
        "defaultLoad": 320,
        "NumofBlocksinOneString": [30, 32, 34, 36, 38, 40, 42, 44, 46],
        "dcEfficiency": [82.5, 93.03, 95.45, 96.05, 96.22, 96.36, 96.37, 96.35, 96.25, 96.16, 96.09],
        "image": "/assets/ups/DPS300-1200.jpg",
        "description": "DPS Series, 3 phase in, 3 phase out, 230V 50 Hz, without battery, parallel function.",
        "modular": false,
        "PM": "N/A"
    },
    {
        "id": 12,
        "PN":"UPS504DS3312A35",
        "name": "DPS 500",
        "price": 61120.88,
        "maxLoad": 500,
        "defaultLoad": 400,
        "NumofBlocksinOneString": [30, 32, 34, 36, 38, 40, 42, 44, 46],
        "dcEfficiency": [82.5, 93.03, 95.45, 96.05, 96.22, 96.36, 96.37, 96.35, 96.25, 96.16, 96.09],
        "image": "/assets/ups/DPS300-1200.jpg",
        "description": "DPS Series, 3 phase in, 3 phase out, 230V 50 Hz, without battery, parallel function.",
        "modular": false,
        "PM": "N/A"
    },
    {
        "id": 13,
        "PN":"UPS604DS3312A35",
        "name": "DPS 600",
        "price": 72439.56,
        "maxLoad": 600,
        "defaultLoad": 480,
        "NumofBlocksinOneString": [30, 32, 34, 36, 38, 40, 42, 44, 46],
        "dcEfficiency": [83.5, 93.03, 95.45, 96.05, 96.22, 96.36, 96.37, 96.35, 96.25, 96.16, 96.09],
        "image": "/assets/ups/DPS300-1200.jpg",
        "description": "DPS Series, 3 phase in, 3 phase out, 230V 50 Hz, without battery, parallel function.",
        "modular": false,
        "PM": "N/A"
    },
    {
        "id": 14,
        "PN":"UPS203HH3300035",
        "name": "HPH G2 20",
        "price": 3758.53,
        "maxLoad": 20,
        "defaultLoad": 20,
        "NumofBlocksinOneString": [30, 32, 34, 36, 38, 40, 42, 44, 46],
        "dcEfficiency": [84, 89.5, 93.2, 94.9, 95.1, 95.2, 95.3, 95.3, 95.3, 95.2, 95.1],
        "image": "/assets/ups/HPH_G2_20-40.jpg",
        "description": "HPH Gen.2 20kVA, tower type, 3P4W 400V.",
        "modular": false,
        "PM": "N/A"
    },
    {
        "id": 15,
        "PN":"UPS303HH3300035",
        "name": "HPH G2 30",
        "price": 4563.08,
        "maxLoad": 30,
        "defaultLoad": 30,
        "NumofBlocksinOneString": [30, 32, 34, 36, 38, 40, 42, 44, 46],
        "dcEfficiency": [83.5, 90.3, 93.1, 94, 94.5, 95, 95, 95.1, 95.1, 95.2, 95.3],
        "image": "/assets/ups/HPH_G2_20-40.jpg",
        "description": "HPH Gen.2 30kVA, tower type, 3P4W 400V.",
        "modular": false,
        "PM": "N/A"
    },
    {
        "id": 16,
        "PN":"UPS403HH3300035",
        "name": "HPH G2 40",
        "price": 5076.48,
        "maxLoad": 40,
        "defaultLoad": 40,
        "NumofBlocksinOneString": [30, 32, 34, 36, 38, 40, 42, 44, 46],
        "dcEfficiency": [83.5, 92, 94.5, 95.2, 95.4, 95.6, 95.5, 95.4, 95.4, 95.4, 95.4],
        "image": "/assets/ups/HPH_G2_20-40.jpg",
        "description": "HPH Gen.2 40kVA, tower type, 3P4W 400V.",
        "modular": false,
        "PM": "N/A"
    },
    {
        "id": 20,
        "PN":"GES603HH330135",
        "name": "HPH 60",
        "price": 7627.44,
        "maxLoad": 60,
        "defaultLoad": 48,
        "NumofBlocksinOneString": [32, 34, 36, 38, 40, 42, 44, 46],
        "dcEfficiency": [84.5, 91.7, 94, 95.08, 95.47, 95.85, 95.91, 96.98, 95.9, 95.68, 95.46],
        "image": "/assets/ups/HPH20-120.jpg",
        "description": "HPH Series 60kVA, 3 phase in, 3 phase out, 230V 50 Hz, without battery, parallel function.",
        "modular": false,
        "PM": "N/A"
    },
    {
        "id": 21,
        "PN":"GES803HH330135",
        "name": "HPH 80",
        "price": 8762.24,
        "maxLoad": 80,
        "defaultLoad": 64,
        "NumofBlocksinOneString": [32, 34, 36, 38, 40, 42, 44, 46],
        "dcEfficiency": [83.7, 90.85, 93.5, 95.03, 95.58, 96.12, 96.04, 95.96, 95.85, 95.72, 95.59],
        "image": "/assets/ups/HPH20-120.jpg",
        "description": "HPH Series 80kVA, 3 phase in, 3 phase out, 230V 50 Hz, without battery, parallel function.",
        "modular": false,
        "PM": "N/A"
    },
    {
        "id": 22,
        "PN":"GES104HH330135",
        "name": "HPH 100",
        "price": 13141.73,
        "maxLoad": 100,
        "defaultLoad": 80,
        "NumofBlocksinOneString": [32, 34, 36, 38, 40, 42, 44, 46],
        "dcEfficiency": [83.7, 90.85, 93.5, 94.41, 94.76, 95.1, 95.2, 95.3, 95.41, 95.52, 95.63],
        "image": "/assets/ups/HPH20-120.jpg",
        "description": "HPH Series 100kVA, 3 phase in, 3 phase out, 230V 50 Hz, without battery, parallel function.",
        "modular": false,
        "PM": "N/A"
    },
    {
        "id": 23,
        "PN":"GES124HH330135",
        "name": "HPH 120",
        "price": 14994.23,
        "maxLoad": 120,
        "defaultLoad": 96,
        "NumofBlocksinOneString": [32, 34, 36, 38, 40, 42, 44, 46],
        "dcEfficiency": [83.7, 90.85, 93.5, 94.35, 94.64, 94.94, 95, 95.06, 94.99, 94.8, 94.6],
        "image": "/assets/ups/HPH20-120.jpg",
        "description": "HPH Series 120kVA, 3 phase in, 3 phase out, 230V 50 Hz, without battery, parallel function.",
        "modular": false,
        "PM": "N/A"
    },
    {
        "id": 24,
        "PN":"GES164HH330035",
        "name": "HPH 160",
        "price": 18905.79,
        "maxLoad": 150,
        "defaultLoad": 150,
        "NumofBlocksinOneString": [30, 32, 34, 36, 38, 40, 42, 44, 46],
        "dcEfficiency": [83.5, 86.2, 89.6, 91.84, 93.45, 94.61, 94.97, 95.34, 95.48, 95.39, 95.3],
        "image": "/assets/ups/HPH160-200.jpg",
        "description": "HPH Series 160kVA, 3 phase in, 3 phase out, 230V 50 Hz, without battery, parallel function.",
        "modular": false,
        "PM": "N/A"
    },
    {
        "id": 25,
        "PN":"GES204HH330035",
        "name": "HPH 200",
        "price": 20476.04,
        "maxLoad": 200,
        "defaultLoad": 200,
        "NumofBlocksinOneString": [30, 32, 34, 36, 38, 40, 42, 44, 46],
        "dcEfficiency": [83.5, 87.7, 91.25, 92.37, 93.16, 93.95, 94.32, 94.69, 94.82, 94.69, 94.57],
        "image": "/assets/ups/HPH160-200.jpg",
        "description": "HPH Series 200kVA, 3 phase in, 3 phase out, 230V 50 Hz, without battery, parallel function.",
        "modular": false,
        "PM": "N/A"
    }
]